modbusreader
