Metadata-Version: 1.1
Name: modbusreader
Version: 1.0.5
Summary: Read values of a modbus server automatically based on a defined config
Home-page: https://github.com/smueller18/modbusreader
Author: Stephan Müller
Author-email: mail@stephanmueller.eu
License: MIT
Download-URL: https://github.com/smueller18/modbusreader
Platform: UNKNOWN
Classifier: Development Status :: 3 - Alpha
Classifier: Programming Language :: Python :: 3.5
Classifier: License :: OSI Approved :: MIT License
